pyAN575/__init__.py
pyAN575-0.1.2.dist-info/LICENSE.txt
pyAN575-0.1.2.dist-info/METADATA
pyAN575-0.1.2.dist-info/WHEEL
pyAN575-0.1.2.dist-info/top_level.txt
pyAN575-0.1.2.dist-info/RECORD
