Metadata-Version: 2.1
Name: pyAN575
Version: 0.1.2
Summary: Converts between Microchip's an575 float format and IEEE-754.
Home-page: https://github.com/ronyb29/pyAN575
Author: Rony Batista
Author-email: rony.batista29@gmail.com
License: UNKNOWN
Keywords: float,ieee754,AN575
Platform: UNKNOWN
Classifier: Programming Language :: Python :: 3
Classifier: License :: OSI Approved :: MIT License
Classifier: Operating System :: OS Independent
